jvcli/__init__.py
jvcli/api.py
jvcli/auth.py
jvcli/cli.py
jvcli/utils.py
jvcli/commands/__init__.py
jvcli/commands/auth.py
jvcli/commands/client.py
jvcli/commands/create.py
jvcli/commands/download.py
jvcli/commands/info.py
jvcli/commands/publish.py
jvcli/commands/server.py
jvcli/commands/startproject.py
jvcli/commands/update.py
jvcli/templates/2.1.25/project/README.md
jvcli/templates/2.1.25/project/env.example
jvcli/templates/2.1.25/project/gitignore.example
jvcli/templates/2.1.25/project/globals.jac
jvcli/templates/2.1.25/project/main.jac
jvcli/templates/2.1.25/project/actions/README.md
jvcli/templates/2.1.25/project/daf/README.md
jvcli/templates/2.1.25/project/tests/README.md
jvcli/templates/2.1.25/sourcefiles/CHANGELOG.md
jvcli/templates/2.1.25/sourcefiles/README.md
jvcli/templates/2.1.25/sourcefiles/action_app.py
jvcli/templates/2.1.25/sourcefiles/action_archetype.jac
jvcli/templates/2.1.25/sourcefiles/action_info.yaml
jvcli/templates/2.1.25/sourcefiles/action_lib.jac
jvcli/templates/2.1.25/sourcefiles/agent_descriptor.yaml
jvcli/templates/2.1.25/sourcefiles/agent_info.yaml
jvcli/templates/2.1.25/sourcefiles/agent_knowledge.yaml
jvcli/templates/2.1.25/sourcefiles/agent_memory.yaml
jvcli/templates/2.1.25/sourcefiles/interact_action_archetype.jac
jvcli-2.1.25.dist-info/licenses/LICENSE
jvcli-2.1.25.dist-info/METADATA
jvcli-2.1.25.dist-info/WHEEL
jvcli-2.1.25.dist-info/entry_points.txt
jvcli-2.1.25.dist-info/top_level.txt
jvcli-2.1.25.dist-info/RECORD
