Metadata-Version: 2.4
Name: jvcli
Version: 2.1.25
Summary: CLI tool for Jivas Package Repository
Home-page: https://github.com/TrueSelph/jvcli
Author: TrueSelph Inc.
Author-email: admin@trueselph.com
Requires-Python: >=3.12
License-File: LICENSE
Requires-Dist: click==8.3.0
Requires-Dist: requests==2.32.5
Requires-Dist: packaging==25.0
Requires-Dist: pyaml==25.7.0
Requires-Dist: python-dotenv==1.2.1
Requires-Dist: semver==3.0.4
Requires-Dist: node-semver>=0.9.0
Requires-Dist: jaclang==0.8.7
Requires-Dist: pymongo==4.11.3
Requires-Dist: uvicorn==0.34.0
Requires-Dist: fastapi==0.115.11
Provides-Extra: dev
Requires-Dist: pre-commit; extra == "dev"
Requires-Dist: pytest; extra == "dev"
Requires-Dist: pytest-mock; extra == "dev"
Requires-Dist: pytest-cov; extra == "dev"
Dynamic: author
Dynamic: author-email
Dynamic: description
Dynamic: description-content-type
Dynamic: home-page
Dynamic: license-file
Dynamic: provides-extra
Dynamic: requires-dist
Dynamic: requires-python
Dynamic: summary
